LICENSE.rst
MANIFEST.in
README.rst
requirements.txt
setup.py
django_slack_invitation.egg-info/PKG-INFO
django_slack_invitation.egg-info/SOURCES.txt
django_slack_invitation.egg-info/dependency_links.txt
django_slack_invitation.egg-info/requires.txt
django_slack_invitation.egg-info/top_level.txt
django_slack_invitation.egg-info/zip-safe
slack_invitation/__init__.py
slack_invitation/compatibility.py
slack_invitation/signals.py
slack_invitation/slack.py
slack_invitation/tests/__init__.py
slack_invitation/tests/compatibility.py
slack_invitation/tests/test_signals.py
slack_invitation/tests/test_slack.py